pypiano/__init__.py
pypiano/keyboard.py
pypiano/piano.py
pypiano/utils.py
pypiano/sound_fonts/FluidR3_GM.sf2
pypiano-0.1.0.dist-info/LICENSE
pypiano-0.1.0.dist-info/METADATA
pypiano-0.1.0.dist-info/WHEEL
pypiano-0.1.0.dist-info/top_level.txt
pypiano-0.1.0.dist-info/RECORD
