Metadata-Version: 2.1
Name: pypiano
Version: 0.1.0
Summary: Library to programmatically play piano
Home-page: https://github.com/FelixGSE/pypiano
Author: FelixGSE
Author-email: 
License: MIT
Platform: UNKNOWN
Requires-Dist: mingus (==0.6.1)
Requires-Dist: numpy (==1.20.2)
Requires-Dist: sf2utils (==0.9.0)
Requires-Dist: requests (==2.25.1)
Requires-Dist: tqdm (==4.60.0)
Requires-Dist: tox (==3.23.0)
Requires-Dist: flake8 (==3.9.1)
Requires-Dist: pyflakes (==2.3.1)
Requires-Dist: pytest (==6.2.3)
